mailparse/__init__.py
mailparse/__version__.py
mailparse/decoder.py
mailparse/encoder.py
mailparse/utils.py
mailparse-1.0.15.dist-info/LICENSE
mailparse-1.0.15.dist-info/METADATA
mailparse-1.0.15.dist-info/WHEEL
mailparse-1.0.15.dist-info/top_level.txt
mailparse-1.0.15.dist-info/RECORD
