Metadata-Version: 2.1
Name: mailparse
Version: 1.0.15
Summary: Encode raw emails into Python dict objects and build raw emails from Python dict.
Home-page: https://github.com/cnicodeme/mailparse
Author: Cyril Nicodeme
Author-email: contact@cnicodeme.com
License: MIT
Project-URL: Source, https://github.com/cnicodeme/mailparse
Keywords: mail email parse parser encode decode encoder decoder eml
Platform: any
Classifier: Development Status :: 5 - Production/Stable
Classifier: Intended Audience :: Developers
Classifier: Topic :: Communications :: Email
Classifier: Topic :: Internet :: WWW/HTTP :: Dynamic Content
Classifier: Topic :: Software Development :: Libraries :: Python Modules
Classifier: Topic :: Utilities
Classifier: Topic :: Scientific/Engineering :: Interface Engine/Protocol Translator
Classifier: Topic :: Text Processing
Classifier: License :: OSI Approved :: MIT License
Classifier: Operating System :: OS Independent
Classifier: Programming Language :: Python
Classifier: Programming Language :: Python :: 3
Classifier: Programming Language :: Python :: 3.3
Classifier: Programming Language :: Python :: 3.4
Classifier: Programming Language :: Python :: 3.5
Classifier: Programming Language :: Python :: 3.6
Classifier: Programming Language :: Python :: 3.7
Classifier: Programming Language :: Python :: 3.8
Classifier: Programming Language :: Python :: 3.9
Classifier: Programming Language :: Python :: 3.10
Classifier: Programming Language :: Python :: Implementation :: PyPy
License-File: LICENSE
